{
  "parent": "minecraft:recipes/root",
  "criteria": {
    "has_the_recipe": {
      "conditions": {
        "recipe": "minecraft:smelt_willow_log_to_charcoal"
      },
      "trigger": "minecraft:recipe_unlocked"
    },
    "has_willow_log": {
      "conditions": {
        "items": [
          {
            "items": "agotmod:willow_log"
          }
        ]
      },
      "trigger": "minecraft:inventory_changed"
    }
  },
  "requirements": [
    [
      "has_the_recipe",
      "has_willow_log"
    ]
  ],
  "rewards": {
    "recipes": [
      "minecraft:smelt_willow_log_to_charcoal"
    ]
  }
}