{
  "parent": "minecraft:recipes/root",
  "criteria": {
    "has_cdeepslate_36": {
      "conditions": {
        "items": [
          {
            "items": "agotmod:cdeepslate_36"
          }
        ]
      },
      "trigger": "minecraft:inventory_changed"
    },
    "has_the_recipe": {
      "conditions": {
        "recipe": "minecraft:cdeepslate_36_stairs_from_cdeepslate_36_block"
      },
      "trigger": "minecraft:recipe_unlocked"
    }
  },
  "requirements": [
    [
      "has_the_recipe",
      "has_cdeepslate_36"
    ]
  ],
  "rewards": {
    "recipes": [
      "minecraft:cdeepslate_36_stairs_from_cdeepslate_36_block"
    ]
  }
}